{
  "sentences": [
    {
      "tokens": [
        {
          "word": "Virus",
          "lemma": "virus",
          "offsetBegin": 0,
          "offsetEnd": 5,
          "pos": "NN"
        },
        {
          "word": "hunting",
          "lemma": "hunting",
          "offsetBegin": 6,
          "offsetEnd": 13,
          "pos": "NN"
        }
      ]
    },
    {
      "tokens": [
        {
          "word": "We",
          "lemma": "we",
          "offsetBegin": 14,
          "offsetEnd": 16,
          "pos": "PRP"
        },
        {
          "word": "all",
          "lemma": "all",
          "offsetBegin": 17,
          "offsetEnd": 20,
          "pos": "DT"
        },
        {
          "word": "appreciate",
          "lemma": "appreciate",
          "offsetBegin": 21,
          "offsetEnd": 31,
          "pos": "VBP"
        },
        {
          "word": "the",
          "lemma": "the",
          "offsetBegin": 32,
          "offsetEnd": 35,
          "pos": "DT"
        },
        {
          "word": "need",
          "lemma": "need",
          "offsetBegin": 36,
          "offsetEnd": 40,
          "pos": "NN"
        },
        {
          "word": "for",
          "lemma": "for",
          "offsetBegin": 41,
          "offsetEnd": 44,
          "pos": "IN"
        },
        {
          "word": ",",
          "lemma": ",",
          "offsetBegin": 44,
          "offsetEnd": 45,
          "pos": ","
        },
        {
          "word": "and",
          "lemma": "and",
          "offsetBegin": 46,
          "offsetEnd": 49,
          "pos": "CC"
        },
        {
          "word": "hopefully",
          "lemma": "hopefully",
          "offsetBegin": 50,
          "offsetEnd": 59,
          "pos": "RB"
        },
        {
          "word": "we",
          "lemma": "we",
          "offsetBegin": 60,
          "offsetEnd": 62,
          "pos": "PRP"
        },
        {
          "word": "have",
          "lemma": "have",
          "offsetBegin": 63,
          "offsetEnd": 67,
          "pos": "VBP"
        },
        {
          "word": "all",
          "lemma": "all",
          "offsetBegin": 68,
          "offsetEnd": 71,
          "pos": "DT"
        },
        {
          "word": "deployed",
          "lemma": "deploy",
          "offsetBegin": 72,
          "offsetEnd": 80,
          "pos": "VBN"
        },
        {
          "word": ",",
          "lemma": ",",
          "offsetBegin": 80,
          "offsetEnd": 81,
          "pos": ","
        },
        {
          "word": "anti-virus",
          "lemma": "anti-virus",
          "offsetBegin": 82,
          "offsetEnd": 92,
          "pos": "JJ"
        },
        {
          "word": "software",
          "lemma": "software",
          "offsetBegin": 93,
          "offsetEnd": 101,
          "pos": "NN"
        },
        {
          "word": ".",
          "lemma": ".",
          "offsetBegin": 101,
          "offsetEnd": 102,
          "pos": "."
        }
      ]
    },
    {
      "tokens": [
        {
          "word": "The",
          "lemma": "the",
          "offsetBegin": 103,
          "offsetEnd": 106,
          "pos": "DT"
        },
        {
          "word": "good",
          "lemma": "good",
          "offsetBegin": 107,
          "offsetEnd": 111,
          "pos": "JJ"
        },
        {
          "word": "news",
          "lemma": "news",
          "offsetBegin": 112,
          "offsetEnd": 116,
          "pos": "NN"
        },
        {
          "word": "is",
          "lemma": "be",
          "offsetBegin": 117,
          "offsetEnd": 119,
          "pos": "VBZ"
        },
        {
          "word": "that",
          "lemma": "that",
          "offsetBegin": 120,
          "offsetEnd": 124,
          "pos": "IN"
        },
        {
          "word": "AV",
          "lemma": "av",
          "offsetBegin": 125,
          "offsetEnd": 127,
          "pos": "NN"
        },
        {
          "word": "software",
          "lemma": "software",
          "offsetBegin": 128,
          "offsetEnd": 136,
          "pos": "NN"
        },
        {
          "word": "has",
          "lemma": "have",
          "offsetBegin": 137,
          "offsetEnd": 140,
          "pos": "VBZ"
        },
        {
          "word": "come",
          "lemma": "come",
          "offsetBegin": 141,
          "offsetEnd": 145,
          "pos": "VBN"
        },
        {
          "word": "a",
          "lemma": "a",
          "offsetBegin": 146,
          "offsetEnd": 147,
          "pos": "DT"
        },
        {
          "word": "long",
          "lemma": "long",
          "offsetBegin": 148,
          "offsetEnd": 152,
          "pos": "JJ"
        },
        {
          "word": "way",
          "lemma": "way",
          "offsetBegin": 153,
          "offsetEnd": 156,
          "pos": "NN"
        },
        {
          "word": "fast",
          "lemma": "fast",
          "offsetBegin": 157,
          "offsetEnd": 161,
          "pos": "RB"
        },
        {
          "word": ".",
          "lemma": ".",
          "offsetBegin": 161,
          "offsetEnd": 162,
          "pos": "."
        }
      ]
    },
    {
      "tokens": [
        {
          "word": "Four",
          "lemma": "four",
          "offsetBegin": 163,
          "offsetEnd": 167,
          "pos": "CD"
        },
        {
          "word": "or",
          "lemma": "or",
          "offsetBegin": 168,
          "offsetEnd": 170,
          "pos": "CC"
        },
        {
          "word": "so",
          "lemma": "so",
          "offsetBegin": 171,
          "offsetEnd": 173,
          "pos": "RB"
        },
        {
          "word": "years",
          "lemma": "year",
          "offsetBegin": 174,
          "offsetEnd": 179,
          "pos": "NNS"
        },
        {
          "word": "ago",
          "lemma": "ago",
          "offsetBegin": 180,
          "offsetEnd": 183,
          "pos": "IN"
        },
        {
          "word": "it",
          "lemma": "it",
          "offsetBegin": 184,
          "offsetEnd": 186,
          "pos": "PRP"
        },
        {
          "word": "was",
          "lemma": "be",
          "offsetBegin": 187,
          "offsetEnd": 190,
          "pos": "VBD"
        },
        {
          "word": "true",
          "lemma": "true",
          "offsetBegin": 191,
          "offsetEnd": 195,
          "pos": "JJ"
        },
        {
          "word": "to",
          "lemma": "to",
          "offsetBegin": 196,
          "offsetEnd": 198,
          "pos": "TO"
        },
        {
          "word": "write",
          "lemma": "write",
          "offsetBegin": 199,
          "offsetEnd": 204,
          "pos": "VB"
        },
        {
          "word": "that",
          "lemma": "that",
          "offsetBegin": 205,
          "offsetEnd": 209,
          "pos": "DT"
        },
        {
          "word": "AV",
          "lemma": "av",
          "offsetBegin": 210,
          "offsetEnd": 212,
          "pos": "NN"
        },
        {
          "word": "software",
          "lemma": "software",
          "offsetBegin": 213,
          "offsetEnd": 221,
          "pos": "NN"
        },
        {
          "word": "could",
          "lemma": "could",
          "offsetBegin": 222,
          "offsetEnd": 227,
          "pos": "MD"
        },
        {
          "word": "not",
          "lemma": "not",
          "offsetBegin": 228,
          "offsetEnd": 231,
          "pos": "RB"
        },
        {
          "word": "detect",
          "lemma": "detect",
          "offsetBegin": 232,
          "offsetEnd": 238,
          "pos": "VB"
        },
        {
          "word": "Trojan",
          "lemma": "Trojan",
          "offsetBegin": 239,
          "offsetEnd": 245,
          "pos": "NNP"
        },
        {
          "word": "Horses",
          "lemma": "horse",
          "offsetBegin": 246,
          "offsetEnd": 252,
          "pos": "NNS"
        },
        {
          "word": "and",
          "lemma": "and",
          "offsetBegin": 253,
          "offsetEnd": 256,
          "pos": "CC"
        },
        {
          "word": "similar",
          "lemma": "similar",
          "offsetBegin": 257,
          "offsetEnd": 264,
          "pos": "JJ"
        },
        {
          "word": "intrusion",
          "lemma": "intrusion",
          "offsetBegin": 265,
          "offsetEnd": 274,
          "pos": "NN"
        },
        {
          "word": "attempts",
          "lemma": "attempt",
          "offsetBegin": 275,
          "offsetEnd": 283,
          "pos": "NNS"
        },
        {
          "word": ".",
          "lemma": ".",
          "offsetBegin": 283,
          "offsetEnd": 284,
          "pos": "."
        }
      ]
    },
    {
      "tokens": [
        {
          "word": "Now",
          "lemma": "now",
          "offsetBegin": 285,
          "offsetEnd": 288,
          "pos": "RB"
        },
        {
          "word": "it",
          "lemma": "it",
          "offsetBegin": 289,
          "offsetEnd": 291,
          "pos": "PRP"
        },
        {
          "word": "can",
          "lemma": "can",
          "offsetBegin": 292,
          "offsetEnd": 295,
          "pos": "MD"
        },
        {
          "word": "and",
          "lemma": "and",
          "offsetBegin": 296,
          "offsetEnd": 299,
          "pos": "CC"
        },
        {
          "word": "does",
          "lemma": "do",
          "offsetBegin": 300,
          "offsetEnd": 304,
          "pos": "VBZ"
        },
        {
          "word": ".",
          "lemma": ".",
          "offsetBegin": 304,
          "offsetEnd": 305,
          "pos": "."
        }
      ]
    },
    {
      "tokens": [
        {
          "word": "McAfee",
          "lemma": "McAfee",
          "offsetBegin": 306,
          "offsetEnd": 312,
          "pos": "NNP"
        },
        {
          "word": "\u0027s",
          "lemma": "\u0027s",
          "offsetBegin": 312,
          "offsetEnd": 314,
          "pos": "POS"
        },
        {
          "word": "VirusScan",
          "lemma": "VirusScan",
          "offsetBegin": 315,
          "offsetEnd": 324,
          "pos": "NNP"
        },
        {
          "word": ",",
          "lemma": ",",
          "offsetBegin": 324,
          "offsetEnd": 325,
          "pos": ","
        },
        {
          "word": "for",
          "lemma": "for",
          "offsetBegin": 326,
          "offsetEnd": 329,
          "pos": "IN"
        },
        {
          "word": "example",
          "lemma": "example",
          "offsetBegin": 330,
          "offsetEnd": 337,
          "pos": "NN"
        },
        {
          "word": ",",
          "lemma": ",",
          "offsetBegin": 337,
          "offsetEnd": 338,
          "pos": ","
        },
        {
          "word": "goes",
          "lemma": "go",
          "offsetBegin": 339,
          "offsetEnd": 343,
          "pos": "VBZ"
        },
        {
          "word": "one",
          "lemma": "one",
          "offsetBegin": 344,
          "offsetEnd": 347,
          "pos": "CD"
        },
        {
          "word": "further",
          "lemma": "further",
          "offsetBegin": 348,
          "offsetEnd": 355,
          "pos": "RB"
        },
        {
          "word": ";",
          "lemma": ";",
          "offsetBegin": 355,
          "offsetEnd": 356,
          "pos": ":"
        },
        {
          "word": "it",
          "lemma": "it",
          "offsetBegin": 357,
          "offsetEnd": 359,
          "pos": "PRP"
        },
        {
          "word": "detects",
          "lemma": "detect",
          "offsetBegin": 360,
          "offsetEnd": 367,
          "pos": "VBZ"
        },
        {
          "word": "viruses",
          "lemma": "virus",
          "offsetBegin": 368,
          "offsetEnd": 375,
          "pos": "NNS"
        },
        {
          "word": ",",
          "lemma": ",",
          "offsetBegin": 375,
          "offsetEnd": 376,
          "pos": ","
        },
        {
          "word": "worms",
          "lemma": "worm",
          "offsetBegin": 377,
          "offsetEnd": 382,
          "pos": "NNS"
        },
        {
          "word": "and",
          "lemma": "and",
          "offsetBegin": 383,
          "offsetEnd": 386,
          "pos": "CC"
        },
        {
          "word": "Trojan",
          "lemma": "Trojan",
          "offsetBegin": 387,
          "offsetEnd": 393,
          "pos": "NNP"
        },
        {
          "word": "Horses",
          "lemma": "horse",
          "offsetBegin": 394,
          "offsetEnd": 400,
          "pos": "NNS"
        },
        {
          "word": "and",
          "lemma": "and",
          "offsetBegin": 401,
          "offsetEnd": 404,
          "pos": "CC"
        },
        {
          "word": "deploys",
          "lemma": "deploy",
          "offsetBegin": 405,
          "offsetEnd": 412,
          "pos": "VBZ"
        },
        {
          "word": "itself",
          "lemma": "itself",
          "offsetBegin": 413,
          "offsetEnd": 419,
          "pos": "PRP"
        },
        {
          "word": "as",
          "lemma": "as",
          "offsetBegin": 420,
          "offsetEnd": 422,
          "pos": "IN"
        },
        {
          "word": "a",
          "lemma": "a",
          "offsetBegin": 423,
          "offsetEnd": 424,
          "pos": "DT"
        },
        {
          "word": "firewall",
          "lemma": "firewall",
          "offsetBegin": 425,
          "offsetEnd": 433,
          "pos": "NN"
        },
        {
          "word": "to",
          "lemma": "to",
          "offsetBegin": 434,
          "offsetEnd": 436,
          "pos": "TO"
        },
        {
          "word": "filter",
          "lemma": "filter",
          "offsetBegin": 437,
          "offsetEnd": 443,
          "pos": "NN"
        },
        {
          "word": "data",
          "lemma": "datum",
          "offsetBegin": 444,
          "offsetEnd": 448,
          "pos": "NNS"
        },
        {
          "word": "packets",
          "lemma": "packet",
          "offsetBegin": 449,
          "offsetEnd": 456,
          "pos": "NNS"
        },
        {
          "word": ",",
          "lemma": ",",
          "offsetBegin": 456,
          "offsetEnd": 457,
          "pos": ","
        },
        {
          "word": "control",
          "lemma": "control",
          "offsetBegin": 458,
          "offsetEnd": 465,
          "pos": "NN"
        },
        {
          "word": "access",
          "lemma": "access",
          "offsetBegin": 466,
          "offsetEnd": 472,
          "pos": "NN"
        },
        {
          "word": "to",
          "lemma": "to",
          "offsetBegin": 473,
          "offsetEnd": 475,
          "pos": "TO"
        },
        {
          "word": "Internet",
          "lemma": "Internet",
          "offsetBegin": 476,
          "offsetEnd": 484,
          "pos": "NNP"
        },
        {
          "word": "resources",
          "lemma": "resource",
          "offsetBegin": 485,
          "offsetEnd": 494,
          "pos": "NNS"
        },
        {
          "word": ",",
          "lemma": ",",
          "offsetBegin": 494,
          "offsetEnd": 495,
          "pos": ","
        },
        {
          "word": "activate",
          "lemma": "activate",
          "offsetBegin": 496,
          "offsetEnd": 504,
          "pos": "VBP"
        },
        {
          "word": "rule",
          "lemma": "rule",
          "offsetBegin": 505,
          "offsetEnd": 509,
          "pos": "NN"
        },
        {
          "word": "sets",
          "lemma": "set",
          "offsetBegin": 510,
          "offsetEnd": 514,
          "pos": "NNS"
        },
        {
          "word": "for",
          "lemma": "for",
          "offsetBegin": 515,
          "offsetEnd": 518,
          "pos": "IN"
        },
        {
          "word": "specific",
          "lemma": "specific",
          "offsetBegin": 519,
          "offsetEnd": 527,
          "pos": "JJ"
        },
        {
          "word": "applications",
          "lemma": "application",
          "offsetBegin": 528,
          "offsetEnd": 540,
          "pos": "NNS"
        },
        {
          "word": ",",
          "lemma": ",",
          "offsetBegin": 540,
          "offsetEnd": 541,
          "pos": ","
        },
        {
          "word": "in",
          "lemma": "in",
          "offsetBegin": 542,
          "offsetEnd": 544,
          "pos": "IN"
        },
        {
          "word": "general",
          "lemma": "general",
          "offsetBegin": 545,
          "offsetEnd": 552,
          "pos": "JJ"
        },
        {
          "word": "to",
          "lemma": "to",
          "offsetBegin": 553,
          "offsetEnd": 555,
          "pos": "TO"
        },
        {
          "word": "protect",
          "lemma": "protect",
          "offsetBegin": 556,
          "offsetEnd": 563,
          "pos": "VB"
        },
        {
          "word": "against",
          "lemma": "against",
          "offsetBegin": 564,
          "offsetEnd": 571,
          "pos": "IN"
        },
        {
          "word": "hackers",
          "lemma": "hacker",
          "offsetBegin": 572,
          "offsetEnd": 579,
          "pos": "NNS"
        },
        {
          "word": ".",
          "lemma": ".",
          "offsetBegin": 579,
          "offsetEnd": 580,
          "pos": "."
        }
      ]
    },
    {
      "tokens": [
        {
          "word": "But",
          "lemma": "but",
          "offsetBegin": 581,
          "offsetEnd": 584,
          "pos": "CC"
        },
        {
          "word": "like",
          "lemma": "like",
          "offsetBegin": 585,
          "offsetEnd": 589,
          "pos": "IN"
        },
        {
          "word": "so",
          "lemma": "so",
          "offsetBegin": 590,
          "offsetEnd": 592,
          "pos": "RB"
        },
        {
          "word": "much",
          "lemma": "much",
          "offsetBegin": 593,
          "offsetEnd": 597,
          "pos": "JJ"
        },
        {
          "word": "software",
          "lemma": "software",
          "offsetBegin": 598,
          "offsetEnd": 606,
          "pos": "NN"
        },
        {
          "word": ",",
          "lemma": ",",
          "offsetBegin": 606,
          "offsetEnd": 607,
          "pos": ","
        },
        {
          "word": "we",
          "lemma": "we",
          "offsetBegin": 608,
          "offsetEnd": 610,
          "pos": "PRP"
        },
        {
          "word": "use",
          "lemma": "use",
          "offsetBegin": 611,
          "offsetEnd": 614,
          "pos": "VBP"
        },
        {
          "word": "it",
          "lemma": "it",
          "offsetBegin": 615,
          "offsetEnd": 617,
          "pos": "PRP"
        },
        {
          "word": "with",
          "lemma": "with",
          "offsetBegin": 618,
          "offsetEnd": 622,
          "pos": "IN"
        },
        {
          "word": "little",
          "lemma": "little",
          "offsetBegin": 623,
          "offsetEnd": 629,
          "pos": "JJ"
        },
        {
          "word": "thought",
          "lemma": "thought",
          "offsetBegin": 630,
          "offsetEnd": 637,
          "pos": "NN"
        },
        {
          "word": "as",
          "lemma": "as",
          "offsetBegin": 638,
          "offsetEnd": 640,
          "pos": "IN"
        },
        {
          "word": "to",
          "lemma": "to",
          "offsetBegin": 641,
          "offsetEnd": 643,
          "pos": "TO"
        },
        {
          "word": "how",
          "lemma": "how",
          "offsetBegin": 644,
          "offsetEnd": 647,
          "pos": "WRB"
        },
        {
          "word": "it",
          "lemma": "it",
          "offsetBegin": 648,
          "offsetEnd": 650,
          "pos": "PRP"
        },
        {
          "word": "came",
          "lemma": "come",
          "offsetBegin": 651,
          "offsetEnd": 655,
          "pos": "VBD"
        },
        {
          "word": "to",
          "lemma": "to",
          "offsetBegin": 656,
          "offsetEnd": 658,
          "pos": "TO"
        },
        {
          "word": "do",
          "lemma": "do",
          "offsetBegin": 659,
          "offsetEnd": 661,
          "pos": "VB"
        },
        {
          "word": "its",
          "lemma": "its",
          "offsetBegin": 662,
          "offsetEnd": 665,
          "pos": "PRP$"
        },
        {
          "word": "job",
          "lemma": "job",
          "offsetBegin": 666,
          "offsetEnd": 669,
          "pos": "NN"
        },
        {
          "word": ".",
          "lemma": ".",
          "offsetBegin": 669,
          "offsetEnd": 670,
          "pos": "."
        }
      ]
    },
    {
      "tokens": [
        {
          "word": "Behind",
          "lemma": "behind",
          "offsetBegin": 671,
          "offsetEnd": 677,
          "pos": "IN"
        },
        {
          "word": "the",
          "lemma": "the",
          "offsetBegin": 678,
          "offsetEnd": 681,
          "pos": "DT"
        },
        {
          "word": "scenes",
          "lemma": "scene",
          "offsetBegin": 682,
          "offsetEnd": 688,
          "pos": "NNS"
        },
        {
          "word": "there",
          "lemma": "there",
          "offsetBegin": 689,
          "offsetEnd": 694,
          "pos": "EX"
        },
        {
          "word": "is",
          "lemma": "be",
          "offsetBegin": 695,
          "offsetEnd": 697,
          "pos": "VBZ"
        },
        {
          "word": "an",
          "lemma": "a",
          "offsetBegin": 698,
          "offsetEnd": 700,
          "pos": "DT"
        },
        {
          "word": "army",
          "lemma": "army",
          "offsetBegin": 701,
          "offsetEnd": 705,
          "pos": "NN"
        },
        {
          "word": "of",
          "lemma": "of",
          "offsetBegin": 706,
          "offsetEnd": 708,
          "pos": "IN"
        },
        {
          "word": "top",
          "lemma": "top",
          "offsetBegin": 709,
          "offsetEnd": 712,
          "pos": "JJ"
        },
        {
          "word": "notch",
          "lemma": "notch",
          "offsetBegin": 713,
          "offsetEnd": 718,
          "pos": "NN"
        },
        {
          "word": "programmers",
          "lemma": "programmer",
          "offsetBegin": 719,
          "offsetEnd": 730,
          "pos": "NNS"
        },
        {
          "word": "trying",
          "lemma": "try",
          "offsetBegin": 731,
          "offsetEnd": 737,
          "pos": "VBG"
        },
        {
          "word": "to",
          "lemma": "to",
          "offsetBegin": 738,
          "offsetEnd": 740,
          "pos": "TO"
        },
        {
          "word": "stay",
          "lemma": "stay",
          "offsetBegin": 741,
          "offsetEnd": 745,
          "pos": "VB"
        },
        {
          "word": "ahead",
          "lemma": "ahead",
          "offsetBegin": 746,
          "offsetEnd": 751,
          "pos": "RB"
        },
        {
          "word": "of",
          "lemma": "of",
          "offsetBegin": 752,
          "offsetEnd": 754,
          "pos": "IN"
        },
        {
          "word": "the",
          "lemma": "the",
          "offsetBegin": 755,
          "offsetEnd": 758,
          "pos": "DT"
        },
        {
          "word": "baddies",
          "lemma": "baddy",
          "offsetBegin": 759,
          "offsetEnd": 766,
          "pos": "NNS"
        },
        {
          "word": "who",
          "lemma": "who",
          "offsetBegin": 767,
          "offsetEnd": 770,
          "pos": "WP"
        },
        {
          "word": ",",
          "lemma": ",",
          "offsetBegin": 770,
          "offsetEnd": 771,
          "pos": ","
        },
        {
          "word": "at",
          "lemma": "at",
          "offsetBegin": 772,
          "offsetEnd": 774,
          "pos": "IN"
        },
        {
          "word": "the",
          "lemma": "the",
          "offsetBegin": 775,
          "offsetEnd": 778,
          "pos": "DT"
        },
        {
          "word": "last",
          "lemma": "last",
          "offsetBegin": 779,
          "offsetEnd": 783,
          "pos": "JJ"
        },
        {
          "word": "count",
          "lemma": "count",
          "offsetBegin": 784,
          "offsetEnd": 789,
          "pos": "NN"
        },
        {
          "word": ",",
          "lemma": ",",
          "offsetBegin": 789,
          "offsetEnd": 790,
          "pos": ","
        },
        {
          "word": "had",
          "lemma": "have",
          "offsetBegin": 791,
          "offsetEnd": 794,
          "pos": "VBD"
        },
        {
          "word": "produced",
          "lemma": "produce",
          "offsetBegin": 795,
          "offsetEnd": 803,
          "pos": "VBN"
        },
        {
          "word": "some",
          "lemma": "some",
          "offsetBegin": 804,
          "offsetEnd": 808,
          "pos": "DT"
        },
        {
          "word": "60,000",
          "lemma": "60,000",
          "offsetBegin": 809,
          "offsetEnd": 815,
          "pos": "CD"
        },
        {
          "word": "viruses",
          "lemma": "virus",
          "offsetBegin": 816,
          "offsetEnd": 823,
          "pos": "NNS"
        }
      ]
    }
  ]
}